pdm_polylith_workspace/polylith/building/__init__.py
pdm_polylith_workspace/polylith/building/core.py
pdm_polylith_workspace/polylith/building/paths.py
pdm_polylith_workspace/polylith/configuration/__init__.py
pdm_polylith_workspace/polylith/configuration/core.py
pdm_polylith_workspace/polylith/parsing/__init__.py
pdm_polylith_workspace/polylith/parsing/core.py
pdm_polylith_workspace/polylith/parsing/rewrite.py
pdm_polylith_workspace/polylith/pdm/__init__.py
pdm_polylith_workspace/polylith/pdm/core.py
pdm_polylith_workspace/polylith/pdm/hooks/__init__.py
pdm_polylith_workspace/polylith/pdm/hooks/bricks.py
pdm_polylith_workspace/polylith/pdm/hooks/workspace.py
pdm_polylith_workspace/polylith/pdm_workspace_hooks/__init__.py
pdm_polylith_workspace/polylith/pdm_workspace_hooks/core.py
pdm_polylith_workspace/polylith/repo/__init__.py
pdm_polylith_workspace/polylith/repo/get.py
pdm_polylith_workspace/polylith/repo/repo.py
pdm_polylith_workspace/polylith/toml/__init__.py
pdm_polylith_workspace/polylith/toml/core.py
pdm_polylith_workspace-1.3.3.dist-info/METADATA
pdm_polylith_workspace-1.3.3.dist-info/WHEEL
pdm_polylith_workspace-1.3.3.dist-info/entry_points.txt
pdm_polylith_workspace-1.3.3.dist-info/RECORD
